AUTHORS.rst
CONTRIBUTING.rst
HISTORY.rst
LICENSE
MANIFEST.in
README.rst
setup.cfg
setup.py
docs/Makefile
docs/authors.rst
docs/conf.py
docs/contributing.rst
docs/history.rst
docs/index.rst
docs/installation.rst
docs/make.bat
docs/modules.rst
docs/readme.rst
docs/usage.rst
docs/_build/html/_static/ajax-loader.gif
docs/_build/html/_static/comment-bright.png
docs/_build/html/_static/comment-close.png
docs/_build/html/_static/comment.png
docs/_build/html/_static/down-pressed.png
docs/_build/html/_static/down.png
docs/_build/html/_static/file.png
docs/_build/html/_static/minus.png
docs/_build/html/_static/plus.png
docs/_build/html/_static/up-pressed.png
docs/_build/html/_static/up.png
pygeons/__init__.py
pygeons/add_alt_names.py
pygeons/api.py
pygeons/db.py
pygeons/initialize.py
pygeons/legacy.py
pygeons/legacy_derive.py
pygeons.egg-info/PKG-INFO
pygeons.egg-info/SOURCES.txt
pygeons.egg-info/dependency_links.txt
pygeons.egg-info/not-zip-safe
pygeons.egg-info/requires.txt
pygeons.egg-info/top_level.txt
tests/__init__.py
tests/capitals.yml
tests/countries.json
tests/csc_scrub_test_data.yml
tests/millionniki.yml
tests/test_integration.py