Metadata-Version: 2.1
Name: pygeons
Version: 0.9.2
Summary: Geographical queries made easy.
Home-page: https://github.com/ProfoundNetworks/pygeons
Author: Michael Penkov
Author-email: m@penkov.dev
License: MIT license
Keywords: pygeons
Platform: UNKNOWN
Classifier: Development Status :: 2 - Pre-Alpha
Classifier: Intended Audience :: Developers
Classifier: License :: OSI Approved :: MIT License
Classifier: Natural Language :: English
Classifier: Programming Language :: Python :: 3
Classifier: Programming Language :: Python :: 3.5
Classifier: Programming Language :: Python :: 3.6
Classifier: Programming Language :: Python :: 3.7
Classifier: Programming Language :: Python :: 3.8
Provides-Extra: test
